{"chunk_definitions":[{"row":247,"row_count":1,"visible":true,"expansion_state":0,"options":{"engine":"r","label":"unnamed-chunk-27"},"document_id":"B755C416","chunk_id":"cs84uvvj6raiq","chunk_label":"unnamed-chunk-8"},{"row":425,"row_count":1,"visible":true,"expansion_state":0,"options":{"engine":"r","label":"unnamed-chunk-84"},"document_id":"B755C416","chunk_id":"cpgfzmejmtk2z","chunk_label":"unnamed-chunk-15"},{"row":555,"row_count":1,"visible":true,"expansion_state":0,"options":{"engine":"r","label":"unnamed-chunk-92"},"document_id":"B755C416","chunk_id":"cok7b923qgqs9","chunk_label":"unnamed-chunk-16"}],"doc_write_time":1598279570}